nntplib.py
nntplib-0.1.3.dist-info/LICENSE
nntplib-0.1.3.dist-info/METADATA
nntplib-0.1.3.dist-info/WHEEL
nntplib-0.1.3.dist-info/top_level.txt
nntplib-0.1.3.dist-info/RECORD
