Metadata-Version: 2.1
Name: nntplib
Version: 0.1.3
Summary: NNTP module from the standard library
Author-email: Matěj Cepl <mcepl@cepl.eu>
License: BSD-3-Clause
Project-URL: Homepage, https://git.cepl.eu/cgit/python/nntplib/
Project-URL: Bug Tracker, https://lists.sr.ht/~mcepl/devel
Keywords: nntp
Classifier: Framework :: Django
Classifier: License :: OSI Approved :: Python Software Foundation License
Classifier: Topic :: Internet
Classifier: Topic :: Communications :: Usenet News
Classifier: Topic :: Software Development :: Libraries
Classifier: Programming Language :: Python :: 3
Classifier: Development Status :: 3 - Alpha
License-File: LICENSE
Requires-Dist: importlib-metadata ; python_version < "3.8"
